{
    "Balance-sheet": {
        "Cash And Cash Equivalents": 48,
        "Equity Share Capital": 48,
        "Fixed Assets": 48,
        "Other Current Liabilities": 48,
        "Reserves and Surplus": 48,
        "Total Assets": 48,
        "Total Capital And Liabilities": 48,
        "Total Current Assets": 48,
        "Total Current Liabilities": 48,
        "Total Non-Current Assets": 48,
        "Total Non-Current Liabilities": 48,
        "Total Reserves and Surplus": 48,
        "Total Share Capital": 48,
        "Total Shareholders Funds": 48,
        "Short Term Provisions": 47,
        "Tangible Assets": 47,
        "Inventories": 46,
        "Short Term Loans And Advances": 46,
        "Trade Payables": 45,
        "Contingent Liabilities": 43,
        "Long Term Borrowings": 43,
        "Non-Current Investments": 43,
        "Trade Receivables": 43,
        "OtherCurrentAssets": 41,
        "Non-Current Investments Unquoted Book Value": 40,
        "Short Term Borrowings": 39,
        "Long Term Provisions": 37,
        "Other Non-Current Assets": 35,
        "Long Term Loans And Advances": 34,
        "Other Long Term Liabilities": 34,
        "Deferred Tax Assets [Net]": 31,
        "Bonus Equity Share Capital": 30,
        "Intangible Assets": 30,
        "Expenditure In Foreign Currency": 29,
        "Deferred Tax Liabilities [Net]": 22,
        "Capital Work-In-Progress": 21,
        "Current Investments": 16,
        "Non-Current Investments Quoted Market Value": 15,
        "Current Investments Unquoted Book Value": 12,
        "Other Earnings": 11,
        "Capital Goods": 5,
        "Raw Materials": 5,
        "Current Investments Quoted Market Value": 4,
        "FOB Value Of Goods": 2,
        "Other Assets": 2
    },
    "Cash-flow": {
        "Cash And Cash Equivalents Begin of Year": 48,
        "Cash And Cash Equivalents End Of Year": 48,
        "Net Cash Used In Investing Activities": 48,
        "Net CashFlow From Operating Activities": 48,
        "Net Inc/Dec In Cash And Cash Equivalents": 48,
        "Net Profit/Loss Before Extraordinary Items And Tax": 48,
        "Net Cash Used From Financing Activities": 46
    },
    "Profit-loss": {
        "Basic EPS (Rs.)": 48,
        "Diluted EPS (Rs.)": 48,
        "Employee Benefit Expenses": 48,
        "Other Expenses": 48,
        "Other Income": 48,
        "Profit/Loss After Tax And Before ExtraOrdinary Items": 48,
        "Profit/Loss Before Exceptional, ExtraOrdinary Items And Tax": 48,
        "Profit/Loss Before Tax": 48,
        "Profit/Loss For The Period": 48,
        "Profit/Loss From Continuing Operations": 48,
        "Total Expenses": 48,
        "Total Operating Revenues": 48,
        "Total Revenue": 48,
        "Total Tax Expenses": 48,
        "Deferred Tax": 47,
        "Depreciation And Amortisation Expenses": 46,
        "Finance Costs": 46,
        "Revenue From Operations [Gross]": 46,
        "Revenue From Operations [Net]": 46,
        "Current Tax": 44,
        "Operating And Direct Expenses": 42,
        "Changes In Inventories Of FG,WIP And Stock-In Trade": 33,
        "Equity Dividend Rate (%)": 28,
        "Equity Share Dividend": 28,
        "Tax On Dividend": 22,
        "Cost Of Materials Consumed": 10,
        "Indigenous Raw Materials": 6,
        "Tax For Earlier Years": 6,
        "Less: Excise/Sevice Tax/Other Levies": 4,
        "Imported Raw Materials": 3,
        "Indigenous Stores And Spares": 3,
        "Purchase Of Stock-In Trade": 2,
        "Exceptional Items": 2,
        "Imported Stores And Spares": 2
    },
    "Quarterly-resul": {
        "Basic EPS": 48,
        "Basic EPS.": 48,
        "Diluted EPS": 48,
        "Diluted EPS.": 48,
        "Employees Cost": 48,
        "Equity Share Capital": 48,
        "Net Profit/(Loss) For the Period": 48,
        "P/L After Tax from Ordinary Activities": 48,
        "P/L Before Exceptional Items & Tax": 48,
        "P/L Before Int., Excpt. Items & Tax": 48,
        "P/L Before Other Inc. , Int., Excpt. Items & Tax": 48,
        "P/L Before Tax": 48,
        "Other Expenses": 47,
        "Total Income From Operations": 46,
        "depreciat": 46,
        "Net Sales/Income from operations": 45,
        "Other Income": 45,
        "Tax": 45,
        "Interest": 43,
        "Increase/Decrease in Stocks": 32,
        "Consumption of Raw Materials": 26,
        "Purchase of Traded Goods": 6,
        "Other Operating Income": 3,
        "Exceptional Items": 2
    },
    "Ratios": {
        "Basic EPS (Rs.)": 48,
        "Book Value [ExclRevalReserve]/Share (Rs.)": 48,
        "Book Value [InclRevalReserve]/Share (Rs.)": 48,
        "Cash EPS (Rs.)": 48,
        "Current Ratio (X)": 48,
        "Diluted EPS (Rs.)": 48,
        "EV/EBITDA (X)": 48,
        "EV/Net Operating Revenue (X)": 48,
        "Earnings Yield": 48,
        "Enterprise Value (Cr.)": 48,
        "MarketCap/Net Operating Revenue (X)": 48,
        "Net Profit Margin (%)": 48,
        "Net Profit/Share (Rs.)": 48,
        "PBDIT Margin (%)": 48,
        "PBDIT/Share (Rs.)": 48,
        "PBIT Margin (%)": 48,
        "PBIT/Share (Rs.)": 48,
        "PBT Margin (%)": 48,
        "PBT/Share (Rs.)": 48,
        "Price/BV (X)": 48,
        "Price/Net Operating Revenue": 48,
        "Quick Ratio (X)": 48,
        "Return on Assets (%)": 48,
        "Return on Capital Employed (%)": 48,
        "Return on Networth / Equity (%)": 48,
        "Revenue from Operations/Share (Rs.)": 48,
        "Asset Turnover Ratio (%)": 47,
        "Total Debt/Equity (X)": 47,
        "Cash Earnings Retention Ratio (%)": 46,
        "Earnings Retention Ratio (%)": 46,
        "Inventory Turnover Ratio (X)": 46,
        "Retention Ratios (%)": 46,
        "Dividend / Share(Rs.)": 44,
        "Dividend Payout Ratio (CP) (%)": 44,
        "Dividend Payout Ratio (NP) (%)": 44
    },
    "Year": {
        "Employees Cost": 47,
        "Equity Share Capital": 47,
        "Net Profit/(Loss) For the Period": 47,
        "Net Sales/Income from operations": 47,
        "Other Expenses": 47,
        "Other Income": 47,
        "P/L After Tax from Ordinary Activities": 47,
        "P/L Before Exceptional Items & Tax": 47,
        "P/L Before Int., Excpt. Items & Tax": 47,
        "P/L Before Other Inc. , Int., Excpt. Items & Tax": 47,
        "P/L Before Tax": 47,
        "Reserves Excluding Revaluation Reserves": 47,
        "Tax": 47,
        "Total Income From Operations": 47,
        "Depreciation": 45,
        "Interest": 44,
        "Basic EPS": 35,
        "Basic EPS.": 35,
        "Diluted EPS": 35,
        "Diluted EPS.": 35,
        "Increase/Decrease in Stocks": 32,
        "Consumption of Raw Materials": 22,
        "Equity Dividend Rate (%)": 21,
        "Share Holding (%)": 14,
        "No Of Shares (Crores)": 12,
        "Other Operating Income": 2,
        "Exceptional Items": 1,
        "Purchase of Traded Goods": 1,
        "Admin. And Selling Expenses": 1
    }
}